Workbook

Sheet Summary
A1: THE BOTTOM LINE
A2: Family of 4 (two children) · eastern Madrid suburbs · home owned outright · no earnings · 2026 € & $
A4: Measure | B4: EUR (€) | C4: USD ($)
A5: Monthly running cost | B5: ='Recurring Costs'!B85 -> 4491.7703 | C5: =B5*'One-Time & Capital'!$B$3 -> 5120.6181
A6: Annual running cost | B6: ='Recurring Costs'!C85 -> 53901.243 | C6: =B6*'One-Time & Capital'!$B$3 -> 61447.417
A7: One-time set-up (home, taxes, furniture, car, move) | B7: ='One-Time & Capital'!B12 -> 328500 | C7: =B7*'One-Time & Capital'!$B$3 -> 374490
A8: Emergency fund (6 months) | B8: ='One-Time & Capital'!B13 -> 26950.622 | C8: =B8*'One-Time & Capital'!$B$3 -> 30723.709
A9: Child-raising fund (both kids, through 18) | B9: ='One-Time & Capital'!B22 -> 117000 | C9: =B9*'One-Time & Capital'!$B$3 -> 133380
A10: Cash needed up front | B10: ='One-Time & Capital'!B15 -> 355450.62 | C10: =B10*'One-Time & Capital'!$B$3 -> 405213.71
A11: TOTAL CAPITAL to fund life with no earnings | B11: ='One-Time & Capital'!B23 -> 1643031.1 | C11: =B11*'One-Time & Capital'!$B$3 -> 1873055.4
A12: TOTAL CAPITAL — tax-adjusted (realistic target) | B12: ='One-Time & Capital'!B29 -> 1806330.8 | C12: =B12*'One-Time & Capital'!$B$3 -> 2059217.1
A14: How to read this
A15: • No earnings → the number that matters most is TOTAL CAPITAL: buy the home, car & furnishings outright, then hold
A16: enough invested that a conservative ~4%/yr draw covers living costs indefinitely.
A17: • Running cost = month-to-month life once settled (no mortgage). Public healthcare & public daycare are free; you've
A18: chosen to keep PRIVATE health insurance on top (€260/mo).
A19: • Husband's technology fund is set equal to the family vacation fund (€8,000/yr) for fairness — it auto-matches, so
A20: if you change the vacation number the tech number follows.
A21: • Replacement reserves: a monthly set-aside (see the 'Replacement Reserves' tab) funds a new EV every 8 years and
A22: renews appliances & furniture over their lifetimes — so nothing is a nasty surprise later.
A23: • Two capital figures: the pre-tax 4% number, and a TAX-ADJUSTED target that grosses up withdrawals for Spanish
A24: investment tax (only gains are taxed, not principal — default ~12% effective; edit it on the One-Time & Capital tab).
A25: • Blue cells = your inputs; black cells = formulas. Everything totals automatically. Not financial advice.
... A27: areas from ~€240k, Cercanías rail into Madrid, malls & services close by.

Sheet Recurring Costs
A1: ANNUAL LIVING BUDGET — Family of 4 (2 children), eastern Madrid commuter belt (Alcalá de Henares area)
A2: Blue = editable monthly inputs. Black = formulas. Annual = Monthly × 12. '(ann.)' = yearly cost shown per month. Private health kept; public daycare free.
A4: Category / Item | B4: Monthly (€) | C4: Annual (€) | D4: Notes / basis
A5: Housing (owned outright — no mortgage)
A6: Utilities — electricity, gas, water, waste | B6: 180 | C6: =B6*12 -> 2160 | D6: Family home incl. AC + heat
A7: Community fees (comunidad: pool, gardens, lift) | B7: 110 | C7: =B7*12 -> 1320 | D7: Gated-community flat
A8: Property tax (IBI) — (ann.) | B8: 45 | C8: =B8*12 -> 540 | D8: ~€540/yr on a ~€265k home
A9: Home maintenance & repairs reserve | B9: 80 | C9: =B9*12 -> 960 | D9: Ongoing upkeep set-aside
A10: Housing (owned outright — no mortgage) — subtotal | B10: =SUM(B6:B9) -> 415 | C10: =SUM(C6:C9) -> 4980
A12: Food & dining
A13: Groceries | B13: 700 | C13: =B13*12 -> 8400 | D13: Family of 4; Mercadona/Lidl
A14: Dining out (2×/month, family) | B14: 150 | C14: =B14*12 -> 1800 | D14: ~€75 per outing
A15: Food & dining — subtotal | B15: =SUM(B13:B14) -> 850 | C15: =SUM(C13:C14) -> 10200
A17: Lifestyle & personal (you)
A18: Entertainment — movies, books, events, friends | B18: 250 | C18: =B18*12 -> 3000
A19: Adult clothing | B19: 120 | C19: =B19*12 -> 1440 | D19: Both adults
A20: Gym membership (couple) | B20: 70 | C20: =B20*12 -> 840
A21: Spanish classes — until fluent (temporary) | B21: 150 | C21: =B21*12 -> 1800 | D21: Drops to €0 once fluent
A22: Toiletries & personal care (incl. makeup, pads) | B22: 80 | C22: =B22*12 -> 960
A23: Haircuts — (ann.) | B23: 25 | C23: =B23*12 -> 300 | D23: ~€300/yr
A24: Lifestyle & personal (you) — subtotal | B24: =SUM(B18:B23) -> 695 | C24: =SUM(C18:C23) -> 8340
A26: Child — Clara (age 5)
A27: Public school fees, books & materials — (ann.) | B27: 35 | C27: =B27*12 -> 420 | D27: Tuition free; ~€400/yr extras
A28: School lunch (comedor) | B28: 120 | C28: =B28*12 -> 1440 | D28: Free/subsidised if you qualify — could be €0
A29: Clothing | B29: 50 | C29: =B29*12 -> 600
A30: Activities / extracurriculars | B30: 80 | C30: =B30*12 -> 960 | D30: Many town-run options are low-cost
A31: Toys | B31: 30 | C31: =B31*12 -> 360
A32: Allowance | B32: 15 | C32: =B32*12 -> 180
A33: Child — Clara (age 5) — subtotal | B33: =SUM(B27:B32) -> 330 | C33: =SUM(C27:C32) -> 3960
A35: Child — second child (from birth)
A36: Daycare / guardería | B36: 0 | C36: =B36*12 -> 0 | D36: FREE — public 0–3 place (Madrid region gratuidad)
A37: Diapers, formula & baby supplies | B37: 120 | C37: =B37*12 -> 1440 | D37: Genuine cost even with free daycare
A38: Baby clothing & gear | B38: 50 | C38: =B38*12 -> 600 | D38: Often hand-me-downs — could be less
A39: Child — second child (from birth) — subtotal | B39: =SUM(B36:B38) -> 170 | C39: =SUM(C36:C38) -> 2040
A41: Family activities & culture
A42: Museums, parks, shows, amusement parks | B42: 120 | C42: =B42*12 -> 1440 | D42: Many Madrid museums free on set days
A43: Family activities & culture — subtotal | B43: =SUM(B42) -> 120 | C43: =SUM(C42) -> 1440
A45: Subscriptions & connectivity
A46: Mobile phones (family) | B46: 50 | C46: =B46*12 -> 600
A47: Home internet (fibre) | B47: 35 | C47: =B47*12 -> 420
A48: Netflix | B48: 14 | C48: =B48*12 -> 168
A49: Amazon Prime — (ann.) | B49: 4 | C49: =B49*12 -> 48 | D49: ~€50/yr
A50: Subscriptions & connectivity — subtotal | B50: =SUM(B46:B49) -> 103 | C50: =SUM(C46:C49) -> 1236
A52: Insurance
A53: Private health — family, no-copay + dental | B53: 260 | C53: =B53*12 -> 3120 | D53: 2 adults + 2 children; kept on TOP of free public system
A54: Life insurance (both adults, term) — optional | B54: 30 | C54: =B54*12 -> 360 | D54: Optional: no mortgage/earnings to replace
A55: Home insurance — (ann.) | B55: 30 | C55: =B55*12 -> 360 | D55: ~€350/yr
A56: Car insurance — (ann.) | B56: 65 | C56: =B56*12 -> 780 | D56: EV comprehensive, slightly higher — ~€780/yr
A57: Insurance — subtotal | B57: =SUM(B53:B56) -> 385 | C57: =SUM(C53:C56) -> 4620
A59: Medical out-of-pocket
A60: Dental, prescriptions, minor extras | B60: 40 | C60: =B60*12 -> 480 | D60: On top of private plan / public cover
A61: Contact lenses — (ann.) | B61: 25 | C61: =B61*12 -> 300 | D61: ~€300/yr
A62: Medical out-of-pocket — subtotal | B62: =SUM(B60:B61) -> 65 | C62: =SUM(C60:C61) -> 780
A64: Transport (1 electric car, owned outright)
A65: Home & public charging | B65: 45 | C65: =B65*12 -> 540 | D65: Mostly home charging ~€0.10–0.15/kWh — far cheaper than petrol
A66: Maintenance, tyres & ITV — (ann.) | B66: 40 | C66: =B66*12 -> 480 | D66: EV: no oil changes, fewer moving parts — ~€480/yr
A67: Road tax (IVTM) — (ann.) | B67: 4 | C67: =B67*12 -> 48 | D67: EV gets big IVTM reduction (often ~75% off)
A68: Public transport passes | B68: 50 | C68: =B68*12 -> 600 | D68: Cercanías into Madrid
A69: Transport (1 electric car, owned outright) — subtotal | B69: =SUM(B65:B68) -> 139 | C69: =SUM(C65:C68) -> 1668
A71: Travel & the matching fund
A72: Family vacation fund — (ann.) | B72: 333.33 | C72: =B72*12 -> 3999.96 | D72: Family-of-4 Disney/US/Japan/Italy rotation — ~€4,000/yr avg (leaner in-between years)
A73: Husband's technology fund — matches vacation (ann.) | B73: =B72 -> 333.33 | C73: =B73*12 -> 3999.96 | D73: Set equal to the vacation fund for fairness — €8,000/yr. Change vacation and this follows.
A74: Travel & the matching fund — subtotal | B74: =SUM(B72:B73) -> 666.66 | C74: =SUM(C72:C73) -> 7999.92
A76: Long-term replacement reserves (sinking funds)
A77: Car / appliances / furniture reserve — see 'Replacement Reserves' tab | B77: ='Replacement Reserves'!F7 -> 363.11027 | C77: =B77*12 -> 4357.3232 | D77: Replace the EV every 8 yrs + appliances & furniture over their lifetimes
A78: Long-term replacement reserves (sinking funds) — subtotal | B78: =SUM(B77) -> 363.11027 | C78: =SUM(C77) -> 4357.3232
A80: Professional services & other
A81: Accountant / gestor — (ann.) | B81: 40 | C81: =B81*12 -> 480 | D81: ~€480/yr — simpler with no earnings
A82: Miscellaneous buffer | B82: 150 | C82: =B82*12 -> 1800 | D82: Real-life extras
A83: Professional services & other — subtotal | B83: =SUM(B81:B82) -> 190 | C83: =SUM(C81:C82) -> 2280
A85: TOTAL RECURRING COST | B85: =B10+B15+B24+B33+B39+B43+B50+B57+B62+B69+B74+B78+B83 -> 4491.7703 | C85: =C10+C15+C24+C33+C39+C43+C50+C57+C62+C69+C74+C78+C83 -> 53901.243 | D85: Full year with young 2nd child + language classes

Sheet One-Time & Capital
A1: ONE-TIME SET-UP & TOTAL CAPITAL NEEDED
A3: EUR → USD rate (editable) | B3: 1.14 | C3: ← change to today's rate
A5: Item | B5: Cost (€) | C5: Cost ($) | D5: Notes
A6: Home purchase price | B6: 250000 | C6: =B6*'One-Time & Capital'!$B$3 -> 285000 | D6: Modern 3-bed/2-bath flat/ground-floor in Alcalá de Henares (or Rivas/Getafe). €250k (~$285k) buys the full spec comfortably here.
A7: Purchase transaction costs (8%) | B7: =B6*0.08 -> 20000 | C7: =B7*'One-Time & Capital'!$B$3 -> 22800 | D7: 6% ITP resale transfer tax + ~2% notary/registry/legal/gestor
A8: Furniture, appliances & kitchen kit | B8: 22000 | C8: =B8*'One-Time & Capital'!$B$3 -> 25080 | D8: Full furnish of a flat; less if kitchen/appliances included
A9: Car — ELECTRIC, purchased outright | B9: 33000 | C9: =B9*'One-Time & Capital'!$B$3 -> 37620 | D9: Family EV (e.g. MG4 / BYD / Megane E-Tech). Range ~€30–38k new; used EVs cheaper.
A10: Home charger (wallbox) + install | B10: 1000 | C10: =B10*'One-Time & Capital'!$B$3 -> 1140 | D10: One-off; €800–1,400, sometimes subsidised
A11: Relocation, moving & admin | B11: 2500 | C11: =B11*'One-Time & Capital'!$B$3 -> 2850 | D11: No visa needed — your husband's citizenship makes residency straightforward
A12: Subtotal — one-time set-up | B12: =SUM(B6:B11) -> 328500 | C12: =B12*'One-Time & Capital'!$B$3 -> 374490
A13: Emergency fund (6 months of living costs) | B13: ='Recurring Costs'!B85*6 -> 26950.622 | C13: =B13*'One-Time & Capital'!$B$3 -> 30723.709 | D13: Cash reserve, not spent
A15: CASH NEEDED UP FRONT (buy everything + reserve) | B15: =B12+B13 -> 355450.62 | C15: =B15*'One-Time & Capital'!$B$3 -> 405213.71
A18: BECAUSE THERE ARE NO EARNINGS: capital to fund life from investments
A19: Safe withdrawal rate (editable) | B19: 0.04
A20: Perpetual household annual (adults, after kids grown) | B20: ='Recurring Costs'!C85-('Recurring Costs'!C33+'Recurring Costs'!C39) -> 47901.243 | C20: =B20*'One-Time & Capital'!$B$3 -> 54607.417 | D20: Full budget minus the kids' current costs (kids funded separately, finite)
A21: Investable capital (perpetual, pre-tax) | B21: =B20/B19 -> 1197531.1 | C21: =B21*'One-Time & Capital'!$B$3 -> 1365185.4 | D21: (perpetual annual / withdrawal rate)
A22: Child-raising fund — both kids through 18 (finite) | B22: ='Children (through 18)'!D7 -> 117000 | C22: =B22*'One-Time & Capital'!$B$3 -> 133380 | D22: See 'Children (through 18)' tab
A23: TOTAL CAPITAL / NEST-EGG (pre-tax) | B23: =B12+B21+B22 -> 1643031.1 | C23: =B23*'One-Time & Capital'!$B$3 -> 1873055.4 | D23: Home+car+furnish + invested pot + kids' fund
A25: TAX-ADJUSTED TARGET (Spanish tax on investment income)
A26: Effective tax rate on withdrawals (editable) | B26: 0.12
A27: Gross withdrawal needed (pre-tax) | B27: =B20/(1-B26) -> 54433.231 | C27: =B27*'One-Time & Capital'!$B$3 -> 62053.883 | D27: So that AFTER tax you still net the perpetual household cost
A28: Tax-adjusted investable capital | B28: =B27/B19 -> 1360830.8 | C28: =B28*'One-Time & Capital'!$B$3 -> 1551347.1 | D28: (gross withdrawal / safe withdrawal rate)
A29: TAX-ADJUSTED TOTAL NEST-EGG | B29: =B12+B28+B22 -> 1806330.8 | C29: =B29*'One-Time & Capital'!$B$3 -> 2059217.1 | D29: After-tax realistic target

Sheet Children (through 18)
A1: CHILD-RAISING FUND — COST THROUGH AGE 18
A2: Kids cost money for a fixed number of years, not forever — so they're funded as a finite lump, added once to the nest-egg (not multiplied by 25). Blue = editable.
A3: Child / phase | B3: Years | C3: Avg annual (€) | D3: Total (€) | E3: Notes
A4: Clara (age 5 → 18) | B4: 13 | C4: 3960 | D4: =B4*C4 -> 51480 | E4: School lunch, clothes, activities, toys, allowance
A5: Second child — baby years (0–3) | B5: 3 | C5: 2040 | D5: =B5*C5 -> 6120 | E5: Diapers, formula, gear (public daycare free)
A6: Second child — ages 3–18 | B6: 15 | C6: 3960 | D6: =B6*C6 -> 59400 | E6: Same child-level costs as Clara
A7: TOTAL child-raising fund (both kids) | D7: =SUM(D4:D6) -> 117000 | E7: Added once to the nest-egg
A9: Excludes university (post-18). Undiscounted — inflation on child costs roughly offsets investment growth over the period.

Sheet Replacement Reserves
A1: LONG-TERM REPLACEMENT RESERVES (SINKING FUNDS)
A2: Annual set-aside = (replacement cost − resale/trade-in) / lifespan. Feeds the monthly budget, so the nest-egg covers replacements forever. Blue = editable.
A3: Item | B3: Replacement cost (€) | C3: Resale at end (€) | D3: Lifespan (yrs) | E3: Annual set-aside (€) | F3: Monthly (€) | G3: Notes
A4: Electric car | B4: ='One-Time & Capital'!B9 -> 33000 | C4: 8000 | D4: 8 | E4: =(B4-C4)/D4 -> 3125 | F4: =E4/12 -> 260.41667 | G4: Replace EV every 8 yrs (battery warranty era). Resale/trade-in ~€8k; cost ties to the purchase price.
A5: Major appliances (fridge, washer, oven, dishwasher…) | B5: 5000 | C5: 0 | D5: 11 | E5: =(B5-C5)/D5 -> 454.54545 | F5: =E5/12 -> 37.878788 | G5: Replaced piecemeal over ~11 yrs on average
A6: Furniture (sofas, beds, dining, wardrobes) | B6: 14000 | C6: 0 | D6: 18 | E6: =(B6-C6)/D6 -> 777.77778 | F6: =E6/12 -> 64.814815 | G6: Refreshed over ~18 yrs — 'as reasonable'
A7: TOTAL replacement reserve | E7: =SUM(E4:E6) -> 4357.3232 | F7: =SUM(F4:F6) -> 363.11027 | G7: Flows into the monthly budget

Sheet Notes & Sources
A1: ASSUMPTIONS, CHOICES & CAVEATS
A3: NO EARNINGS — You'll fund everything from savings/investments, so the headline is the TOTAL CAPITAL figure on the
A4: Summary tab, not a salary. Buy the home, car and furniture outright, then keep an invested pot large enough that a
A5: conservative ~4% annual draw covers running costs. Withdrawals / investment income are taxable in Spain (savings tax
A6: ~19–28% in bands), so the real pot needs to be somewhat larger than the raw 4% maths — a gestor can structure this.
A8: PRIVATE HEALTH INSURANCE — Kept, as you asked (€260/mo for the family, no-copay, with a dental rider). This sits on
A9: TOP of the free public system your family can use through your husband's citizenship — so you get public cover as a
A10: safety net plus private speed/choice/English-speaking doctors. Prescriptions & dental extras sit in 'medical out-of-pocket'.
A12: HUSBAND'S TECHNOLOGY FUND = VACATION FUND — Per your note, your husband gets a technology budget equal to the
A13: vacation fund: €8,000/yr (≈€667/mo). In the sheet this cell is a FORMULA locked to the vacation line, so the two always
A14: stay equal — raise or lower vacations and the tech budget mirrors it. (It replaced the small shared tech line and the
A15: one-off tech set-up amount from the earlier version.)
... A40: Madrid regional education (0–3 gratuidad); car-cost guides; ECB / Bloomberg (EUR-USD ≈ 1.14).
